pynamicui/__init__.py
pynamicui/createDom/__init__.py
pynamicui/createDom/createDom.py
pynamicui/createElement/__init__.py
pynamicui/createElement/createElement.py
pynamicui/createPageViewer/__init__.py
pynamicui/createPageViewer/createPageViewer.py
pynamicui/createStylesheet/__init__.py
pynamicui/createStylesheet/createStylesheet.py
pynamicui-0.1.0.dist-info/LICENSE
pynamicui-0.1.0.dist-info/METADATA
pynamicui-0.1.0.dist-info/WHEEL
pynamicui-0.1.0.dist-info/top_level.txt
pynamicui-0.1.0.dist-info/RECORD
