Metadata-Version: 2.1
Name: pynamicui
Version: 0.1.0
Summary: dynamic web-like UIs using a declarative syntax
Home-page: https://github.com/zacharie410/PynamicUI
Author: zacharie410
License: Apache Software License
Classifier: License :: OSI Approved :: Apache Software License
Classifier: Operating System :: OS Independent
Classifier: Programming Language :: Python :: 3 :: Only
Requires-Python: >=3.7
License-File: LICENSE
Requires-Dist: customtkinter
